perceptron/__init__.py
perceptron/perceptron.py
perceptron_pypi_diptesh_km-0.0.1.dist-info/LICENSE
perceptron_pypi_diptesh_km-0.0.1.dist-info/METADATA
perceptron_pypi_diptesh_km-0.0.1.dist-info/WHEEL
perceptron_pypi_diptesh_km-0.0.1.dist-info/top_level.txt
perceptron_pypi_diptesh_km-0.0.1.dist-info/RECORD
