Metadata-Version: 2.1
Name: perceptron-pypi-diptesh-km
Version: 0.0.1
Summary: its an implementation of Perceptron
Home-page: https://github.com/diptesh_km/perceptron_pypi
Author: diptesh_km
Author-email: diptesh.km@gmail.com
License: UNKNOWN
Project-URL: Bug Tracker, https://github.com/diptesh_km/perceptron_pypi/issues
Platform: UNKNOWN
Classifier: Programming Language :: Python :: 3
Classifier: License :: OSI Approved :: MIT License
Classifier: Operating System :: OS Independent
Requires-Python: >=3.7
License-File: LICENSE
Requires-Dist: numpy
Requires-Dist: tqdm
